mdlogger/__init__.py
mdlogger/core/__init__.py
mdlogger/core/markdown_logger.py
mdlogger/decorator/__init__.py
mdlogger-0.1.dist-info/LICENSE
mdlogger-0.1.dist-info/METADATA
mdlogger-0.1.dist-info/WHEEL
mdlogger-0.1.dist-info/top_level.txt
mdlogger-0.1.dist-info/RECORD
