Metadata-Version: 2.1
Name: mdlogger
Version: 0.1
License-File: LICENSE
